mfc/__init__.py
mfc/driver.py
mfc-0.4.0.dist-info/LICENSE
mfc-0.4.0.dist-info/METADATA
mfc-0.4.0.dist-info/WHEEL
mfc-0.4.0.dist-info/entry_points.txt
mfc-0.4.0.dist-info/top_level.txt
mfc-0.4.0.dist-info/RECORD
