Metadata-Version: 2.1
Name: mfc
Version: 0.4.0
Summary: Python driver for MKS mass flow controllers.
Home-page: http://github.com/numat/mfc/
Author: Patrick Fuller
Author-email: pat@numat-tech.com
License: GPLv2
Platform: UNKNOWN
Classifier: License :: OSI Approved :: GNU General Public License v2 (GPLv2)
Classifier: Development Status :: 4 - Beta
Classifier: Natural Language :: English
Classifier: Programming Language :: Python
Classifier: Programming Language :: Python :: 3
Classifier: Programming Language :: Python :: 3.5
Classifier: Programming Language :: Python :: 3.6
Classifier: Programming Language :: Python :: 3.7
Classifier: Programming Language :: Python :: 3.8
Classifier: Programming Language :: Python :: 3.9
Classifier: Topic :: Scientific/Engineering :: Human Machine Interfaces
License-File: LICENSE
Requires-Dist: aiohttp (>=3.3)
